iofy/__init__.py
iofy-0.1.dist-info/METADATA
iofy-0.1.dist-info/WHEEL
iofy-0.1.dist-info/top_level.txt
iofy-0.1.dist-info/RECORD
